{
  "generated_at": "2026-07-13T23:54:43.930916+00:00",
  "source": "football-data.org",
  "dates": [
    "2026-07-14",
    "2026-07-15"
  ],
  "competitions": [
    "WC",
    "PL",
    "CL"
  ],
  "count": 1,
  "fixtures": [
    {
      "id": 537387,
      "date": "2026-07-14T19:00:00Z",
      "status": "NS",
      "status_text": "TIMED",
      "matchday": null,
      "stage": "SEMI_FINALS",
      "group": null,
      "venue": null,
      "league": {
        "code": "WC",
        "name": "FIFA World Cup",
        "country": "",
        "season": "2026"
      },
      "home": {
        "id": 773,
        "name": "France",
        "tla": "FRA",
        "logo": "https://crests.football-data.org/773.svg"
      },
      "away": {
        "id": 760,
        "name": "Spain",
        "tla": "ESP",
        "logo": "https://crests.football-data.org/760.svg"
      },
      "goals": {
        "home": null,
        "away": null
      }
    }
  ]
}