{
  "fixture_id": 537331,
  "date": "2026-06-25T01:00:00Z",
  "status": "FT",
  "venue": null,
  "league": {
    "code": "WC",
    "name": "FIFA World Cup",
    "country": "",
    "season": "2026"
  },
  "home": {
    "id": 798,
    "name": "Czechia",
    "tla": "CZE",
    "logo": "https://crests.football-data.org/798.svg",
    "form": [
      "L",
      "D",
      "L"
    ],
    "restDays": 0,
    "players": [
      {
        "name": "Matej Kovár",
        "pos": "GK",
        "shirt": "1",
        "starter": true,
        "ovr": 80,
        "pac": 0,
        "sho": 0,
        "pas": 0,
        "dri": 0,
        "def": 0,
        "phy": 0,
        "sta": 80,
        "restDays": 0,
        "load3": 240,
        "lastRating": 7.0,
        "err3": 0,
        "status": "avail",
        "reason": ""
      },
      {
        "name": "Robin Hranác",
        "pos": "DF",
        "shirt": "4",
        "starter": true,
        "ovr": 78,
        "pac": 74,
        "sho": 40,
        "pas": 70,
        "dri": 66,
        "def": 84,
        "phy": 82,
        "sta": 84,
        "restDays": 0,
        "load3": 240,
        "lastRating": 7.0,
        "err3": 0,
        "status": "avail",
        "reason": ""
      },
      {
        "name": "Ladislav Krejcí",
        "pos": "DF",
        "shirt": "7",
        "starter": true,
        "ovr": 78,
        "pac": 74,
        "sho": 40,
        "pas": 70,
        "dri": 66,
        "def": 84,
        "phy": 82,
        "sta": 84,
        "restDays": 0,
        "load3": 240,
        "lastRating": 7.0,
        "err3": 0,
        "status": "avail",
        "reason": ""
      },
      {
        "name": "Tomás Holes",
        "pos": "DF",
        "shirt": "3",
        "starter": true,
        "ovr": 78,
        "pac": 74,
        "sho": 40,
        "pas": 70,
        "dri": 66,
        "def": 84,
        "phy": 82,
        "sta": 84,
        "restDays": 0,
        "load3": 240,
        "lastRating": 7.0,
        "err3": 0,
        "status": "avail",
        "reason": ""
      },
      {
        "name": "Michal Sadílek",
        "pos": "MF",
        "shirt": "18",
        "starter": true,
        "ovr": 80,
        "pac": 72,
        "sho": 68,
        "pas": 80,
        "dri": 76,
        "def": 76,
        "phy": 78,
        "sta": 86,
        "restDays": 0,
        "load3": 240,
        "lastRating": 7.0,
        "err3": 0,
        "status": "avail",
        "reason": ""
      },
      {
        "name": "Lukás Cerv",
        "pos": "MF",
        "shirt": "12",
        "starter": true,
        "ovr": 80,
        "pac": 72,
        "sho": 68,
        "pas": 80,
        "dri": 76,
        "def": 76,
        "phy": 78,
        "sta": 86,
        "restDays": 0,
        "load3": 240,
        "lastRating": 7.0,
        "err3": 0,
        "status": "avail",
        "reason": ""
      },
      {
        "name": "David Doudera",
        "pos": "MF",
        "shirt": "21",
        "starter": true,
        "ovr": 80,
        "pac": 72,
        "sho": 68,
        "pas": 80,
        "dri": 76,
        "def": 76,
        "phy": 78,
        "sta": 86,
        "restDays": 0,
        "load3": 240,
        "lastRating": 7.0,
        "err3": 0,
        "status": "avail",
        "reason": ""
      },
      {
        "name": "Vladimír Coufal",
        "pos": "MF",
        "shirt": "5",
        "starter": true,
        "ovr": 80,
        "pac": 72,
        "sho": 68,
        "pas": 80,
        "dri": 76,
        "def": 76,
        "phy": 78,
        "sta": 86,
        "restDays": 0,
        "load3": 240,
        "lastRating": 7.0,
        "err3": 0,
        "status": "avail",
        "reason": ""
      },
      {
        "name": "Adam Hlozek",
        "pos": "FW",
        "shirt": "9",
        "starter": true,
        "ovr": 80,
        "pac": 80,
        "sho": 80,
        "pas": 75,
        "dri": 80,
        "def": 35,
        "phy": 70,
        "sta": 82,
        "restDays": 0,
        "load3": 240,
        "lastRating": 7.0,
        "err3": 0,
        "status": "avail",
        "reason": ""
      },
      {
        "name": "Denis Visinský",
        "pos": "FW",
        "shirt": "26",
        "starter": true,
        "ovr": 80,
        "pac": 80,
        "sho": 80,
        "pas": 75,
        "dri": 80,
        "def": 35,
        "phy": 70,
        "sta": 82,
        "restDays": 0,
        "load3": 240,
        "lastRating": 7.0,
        "err3": 0,
        "status": "avail",
        "reason": ""
      },
      {
        "name": "Pavel Sulc",
        "pos": "FW",
        "shirt": "15",
        "starter": true,
        "ovr": 80,
        "pac": 80,
        "sho": 80,
        "pas": 75,
        "dri": 80,
        "def": 35,
        "phy": 70,
        "sta": 82,
        "restDays": 0,
        "load3": 240,
        "lastRating": 7.0,
        "err3": 0,
        "status": "avail",
        "reason": ""
      },
      {
        "name": "Lukás Provod",
        "pos": "MF",
        "shirt": "17",
        "starter": false,
        "ovr": 80,
        "pac": 72,
        "sho": 68,
        "pas": 80,
        "dri": 76,
        "def": 76,
        "phy": 78,
        "sta": 86,
        "restDays": 0,
        "load3": 240,
        "lastRating": 7.0,
        "err3": 0,
        "status": "avail",
        "reason": ""
      },
      {
        "name": "David Zima",
        "pos": "MF",
        "shirt": "2",
        "starter": false,
        "ovr": 80,
        "pac": 72,
        "sho": 68,
        "pas": 80,
        "dri": 76,
        "def": 76,
        "phy": 78,
        "sta": 86,
        "restDays": 0,
        "load3": 240,
        "lastRating": 7.0,
        "err3": 0,
        "status": "avail",
        "reason": ""
      },
      {
        "name": "Jaroslav Zelený",
        "pos": "MF",
        "shirt": "20",
        "starter": false,
        "ovr": 80,
        "pac": 72,
        "sho": 68,
        "pas": 80,
        "dri": 76,
        "def": 76,
        "phy": 78,
        "sta": 86,
        "restDays": 0,
        "load3": 240,
        "lastRating": 7.0,
        "err3": 0,
        "status": "avail",
        "reason": ""
      },
      {
        "name": "Lukás Hornícek",
        "pos": "MF",
        "shirt": "23",
        "starter": false,
        "ovr": 80,
        "pac": 72,
        "sho": 68,
        "pas": 80,
        "dri": 76,
        "def": 76,
        "phy": 78,
        "sta": 86,
        "restDays": 0,
        "load3": 240,
        "lastRating": 7.0,
        "err3": 0,
        "status": "avail",
        "reason": ""
      },
      {
        "name": "Hugo Sochurek",
        "pos": "MF",
        "shirt": "25",
        "starter": false,
        "ovr": 80,
        "pac": 72,
        "sho": 68,
        "pas": 80,
        "dri": 76,
        "def": 76,
        "phy": 78,
        "sta": 86,
        "restDays": 0,
        "load3": 240,
        "lastRating": 7.0,
        "err3": 0,
        "status": "avail",
        "reason": ""
      },
      {
        "name": "Tomás Chorý",
        "pos": "MF",
        "shirt": "19",
        "starter": false,
        "ovr": 80,
        "pac": 72,
        "sho": 68,
        "pas": 80,
        "dri": 76,
        "def": 76,
        "phy": 78,
        "sta": 86,
        "restDays": 0,
        "load3": 240,
        "lastRating": 7.0,
        "err3": 0,
        "status": "avail",
        "reason": ""
      },
      {
        "name": "Stepán Chaloupek",
        "pos": "MF",
        "shirt": "6",
        "starter": false,
        "ovr": 80,
        "pac": 72,
        "sho": 68,
        "pas": 80,
        "dri": 76,
        "def": 76,
        "phy": 78,
        "sta": 86,
        "restDays": 0,
        "load3": 240,
        "lastRating": 7.0,
        "err3": 0,
        "status": "avail",
        "reason": ""
      },
      {
        "name": "Patrik Schick",
        "pos": "MF",
        "shirt": "10",
        "starter": false,
        "ovr": 80,
        "pac": 72,
        "sho": 68,
        "pas": 80,
        "dri": 76,
        "def": 76,
        "phy": 78,
        "sta": 86,
        "restDays": 0,
        "load3": 240,
        "lastRating": 7.0,
        "err3": 0,
        "status": "avail",
        "reason": ""
      },
      {
        "name": "Jan Kuchta",
        "pos": "MF",
        "shirt": "11",
        "starter": false,
        "ovr": 80,
        "pac": 72,
        "sho": 68,
        "pas": 80,
        "dri": 76,
        "def": 76,
        "phy": 78,
        "sta": 86,
        "restDays": 0,
        "load3": 240,
        "lastRating": 7.0,
        "err3": 0,
        "status": "avail",
        "reason": ""
      },
      {
        "name": "Mojmír Chytil",
        "pos": "MF",
        "shirt": "13",
        "starter": false,
        "ovr": 80,
        "pac": 72,
        "sho": 68,
        "pas": 80,
        "dri": 76,
        "def": 76,
        "phy": 78,
        "sta": 86,
        "restDays": 0,
        "load3": 240,
        "lastRating": 7.0,
        "err3": 0,
        "status": "avail",
        "reason": ""
      },
      {
        "name": "Tomás Soucek",
        "pos": "MF",
        "shirt": "22",
        "starter": false,
        "ovr": 80,
        "pac": 72,
        "sho": 68,
        "pas": 80,
        "dri": 76,
        "def": 76,
        "phy": 78,
        "sta": 86,
        "restDays": 0,
        "load3": 240,
        "lastRating": 7.0,
        "err3": 0,
        "status": "avail",
        "reason": ""
      },
      {
        "name": "Vladimír Darida",
        "pos": "MF",
        "shirt": "8",
        "starter": false,
        "ovr": 80,
        "pac": 72,
        "sho": 68,
        "pas": 80,
        "dri": 76,
        "def": 76,
        "phy": 78,
        "sta": 86,
        "restDays": 0,
        "load3": 240,
        "lastRating": 7.0,
        "err3": 0,
        "status": "avail",
        "reason": ""
      },
      {
        "name": "Jindrich Stanek",
        "pos": "MF",
        "shirt": "16",
        "starter": false,
        "ovr": 80,
        "pac": 72,
        "sho": 68,
        "pas": 80,
        "dri": 76,
        "def": 76,
        "phy": 78,
        "sta": 86,
        "restDays": 0,
        "load3": 240,
        "lastRating": 7.0,
        "err3": 0,
        "status": "avail",
        "reason": ""
      },
      {
        "name": "Alexandr Sojka",
        "pos": "MF",
        "shirt": "24",
        "starter": false,
        "ovr": 80,
        "pac": 72,
        "sho": 68,
        "pas": 80,
        "dri": 76,
        "def": 76,
        "phy": 78,
        "sta": 86,
        "restDays": 0,
        "load3": 240,
        "lastRating": 7.0,
        "err3": 0,
        "status": "avail",
        "reason": ""
      }
    ],
    "lineup_confirmed": true,
    "formation": "3-4-2-1"
  },
  "away": {
    "id": 769,
    "name": "Mexico",
    "tla": "MEX",
    "logo": "https://crests.football-data.org/769.svg",
    "form": [
      "W",
      "W",
      "W"
    ],
    "restDays": 0,
    "players": [
      {
        "name": "Raúl Rangel",
        "pos": "GK",
        "shirt": "1",
        "starter": true,
        "ovr": 80,
        "pac": 0,
        "sho": 0,
        "pas": 0,
        "dri": 0,
        "def": 0,
        "phy": 0,
        "sta": 80,
        "restDays": 0,
        "load3": 240,
        "lastRating": 7.0,
        "err3": 0,
        "status": "avail",
        "reason": ""
      },
      {
        "name": "Israel Reyes",
        "pos": "DF",
        "shirt": "15",
        "starter": true,
        "ovr": 78,
        "pac": 74,
        "sho": 40,
        "pas": 70,
        "dri": 66,
        "def": 84,
        "phy": 82,
        "sta": 84,
        "restDays": 0,
        "load3": 240,
        "lastRating": 7.0,
        "err3": 0,
        "status": "avail",
        "reason": ""
      },
      {
        "name": "César Montes",
        "pos": "DF",
        "shirt": "3",
        "starter": true,
        "ovr": 78,
        "pac": 74,
        "sho": 40,
        "pas": 70,
        "dri": 66,
        "def": 84,
        "phy": 82,
        "sta": 84,
        "restDays": 0,
        "load3": 240,
        "lastRating": 7.0,
        "err3": 0,
        "status": "avail",
        "reason": ""
      },
      {
        "name": "Mateo Chávez",
        "pos": "DF",
        "shirt": "20",
        "starter": true,
        "ovr": 78,
        "pac": 74,
        "sho": 40,
        "pas": 70,
        "dri": 66,
        "def": 84,
        "phy": 82,
        "sta": 84,
        "restDays": 0,
        "load3": 240,
        "lastRating": 7.0,
        "err3": 0,
        "status": "avail",
        "reason": ""
      },
      {
        "name": "Jorge Sánchez",
        "pos": "DF",
        "shirt": "2",
        "starter": true,
        "ovr": 78,
        "pac": 74,
        "sho": 40,
        "pas": 70,
        "dri": 66,
        "def": 84,
        "phy": 82,
        "sta": 84,
        "restDays": 0,
        "load3": 240,
        "lastRating": 7.0,
        "err3": 0,
        "status": "avail",
        "reason": ""
      },
      {
        "name": "Edson Álvarez",
        "pos": "MF",
        "shirt": "4",
        "starter": true,
        "ovr": 80,
        "pac": 72,
        "sho": 68,
        "pas": 80,
        "dri": 76,
        "def": 76,
        "phy": 78,
        "sta": 86,
        "restDays": 0,
        "load3": 240,
        "lastRating": 7.0,
        "err3": 0,
        "status": "avail",
        "reason": ""
      },
      {
        "name": "Luis Romo",
        "pos": "MF",
        "shirt": "7",
        "starter": true,
        "ovr": 80,
        "pac": 72,
        "sho": 68,
        "pas": 80,
        "dri": 76,
        "def": 76,
        "phy": 78,
        "sta": 86,
        "restDays": 0,
        "load3": 240,
        "lastRating": 7.0,
        "err3": 0,
        "status": "avail",
        "reason": ""
      },
      {
        "name": "Gilberto Mora",
        "pos": "MF",
        "shirt": "19",
        "starter": true,
        "ovr": 80,
        "pac": 72,
        "sho": 68,
        "pas": 80,
        "dri": 76,
        "def": 76,
        "phy": 78,
        "sta": 86,
        "restDays": 0,
        "load3": 240,
        "lastRating": 7.0,
        "err3": 0,
        "status": "avail",
        "reason": ""
      },
      {
        "name": "Guillermo Martínez",
        "pos": "FW",
        "shirt": "22",
        "starter": true,
        "ovr": 80,
        "pac": 80,
        "sho": 80,
        "pas": 75,
        "dri": 80,
        "def": 35,
        "phy": 70,
        "sta": 82,
        "restDays": 0,
        "load3": 240,
        "lastRating": 7.0,
        "err3": 0,
        "status": "avail",
        "reason": ""
      },
      {
        "name": "Julián Quiñones",
        "pos": "FW",
        "shirt": "16",
        "starter": true,
        "ovr": 80,
        "pac": 80,
        "sho": 80,
        "pas": 75,
        "dri": 80,
        "def": 35,
        "phy": 70,
        "sta": 82,
        "restDays": 0,
        "load3": 240,
        "lastRating": 7.0,
        "err3": 0,
        "status": "avail",
        "reason": ""
      },
      {
        "name": "Roberto Alvarado",
        "pos": "FW",
        "shirt": "25",
        "starter": true,
        "ovr": 80,
        "pac": 80,
        "sho": 80,
        "pas": 75,
        "dri": 80,
        "def": 35,
        "phy": 70,
        "sta": 82,
        "restDays": 0,
        "load3": 240,
        "lastRating": 7.0,
        "err3": 0,
        "status": "avail",
        "reason": ""
      },
      {
        "name": "Jesús Gallardo",
        "pos": "MF",
        "shirt": "23",
        "starter": false,
        "ovr": 80,
        "pac": 72,
        "sho": 68,
        "pas": 80,
        "dri": 76,
        "def": 76,
        "phy": 78,
        "sta": 86,
        "restDays": 0,
        "load3": 240,
        "lastRating": 7.0,
        "err3": 0,
        "status": "avail",
        "reason": ""
      },
      {
        "name": "Johan Vásquez",
        "pos": "MF",
        "shirt": "5",
        "starter": false,
        "ovr": 80,
        "pac": 72,
        "sho": 68,
        "pas": 80,
        "dri": 76,
        "def": 76,
        "phy": 78,
        "sta": 86,
        "restDays": 0,
        "load3": 240,
        "lastRating": 7.0,
        "err3": 0,
        "status": "avail",
        "reason": ""
      },
      {
        "name": "Orbelín Pineda",
        "pos": "MF",
        "shirt": "17",
        "starter": false,
        "ovr": 80,
        "pac": 72,
        "sho": 68,
        "pas": 80,
        "dri": 76,
        "def": 76,
        "phy": 78,
        "sta": 86,
        "restDays": 0,
        "load3": 240,
        "lastRating": 7.0,
        "err3": 0,
        "status": "avail",
        "reason": ""
      },
      {
        "name": "Érik Lira",
        "pos": "MF",
        "shirt": "6",
        "starter": false,
        "ovr": 80,
        "pac": 72,
        "sho": 68,
        "pas": 80,
        "dri": 76,
        "def": 76,
        "phy": 78,
        "sta": 86,
        "restDays": 0,
        "load3": 240,
        "lastRating": 7.0,
        "err3": 0,
        "status": "avail",
        "reason": ""
      },
      {
        "name": "César Huerta",
        "pos": "MF",
        "shirt": "21",
        "starter": false,
        "ovr": 80,
        "pac": 72,
        "sho": 68,
        "pas": 80,
        "dri": 76,
        "def": 76,
        "phy": 78,
        "sta": 86,
        "restDays": 0,
        "load3": 240,
        "lastRating": 7.0,
        "err3": 0,
        "status": "avail",
        "reason": ""
      },
      {
        "name": "Raúl Jiménez",
        "pos": "MF",
        "shirt": "9",
        "starter": false,
        "ovr": 80,
        "pac": 72,
        "sho": 68,
        "pas": 80,
        "dri": 76,
        "def": 76,
        "phy": 78,
        "sta": 86,
        "restDays": 0,
        "load3": 240,
        "lastRating": 7.0,
        "err3": 0,
        "status": "avail",
        "reason": ""
      },
      {
        "name": "Luis Chávez",
        "pos": "MF",
        "shirt": "24",
        "starter": false,
        "ovr": 80,
        "pac": 72,
        "sho": 68,
        "pas": 80,
        "dri": 76,
        "def": 76,
        "phy": 78,
        "sta": 86,
        "restDays": 0,
        "load3": 240,
        "lastRating": 7.0,
        "err3": 0,
        "status": "avail",
        "reason": ""
      },
      {
        "name": "Armando González",
        "pos": "MF",
        "shirt": "14",
        "starter": false,
        "ovr": 80,
        "pac": 72,
        "sho": 68,
        "pas": 80,
        "dri": 76,
        "def": 76,
        "phy": 78,
        "sta": 86,
        "restDays": 0,
        "load3": 240,
        "lastRating": 7.0,
        "err3": 0,
        "status": "avail",
        "reason": ""
      },
      {
        "name": "Alexis Vega",
        "pos": "MF",
        "shirt": "10",
        "starter": false,
        "ovr": 80,
        "pac": 72,
        "sho": 68,
        "pas": 80,
        "dri": 76,
        "def": 76,
        "phy": 78,
        "sta": 86,
        "restDays": 0,
        "load3": 240,
        "lastRating": 7.0,
        "err3": 0,
        "status": "avail",
        "reason": ""
      },
      {
        "name": "Guillermo Ochoa",
        "pos": "MF",
        "shirt": "13",
        "starter": false,
        "ovr": 80,
        "pac": 72,
        "sho": 68,
        "pas": 80,
        "dri": 76,
        "def": 76,
        "phy": 78,
        "sta": 86,
        "restDays": 0,
        "load3": 240,
        "lastRating": 7.0,
        "err3": 0,
        "status": "avail",
        "reason": ""
      },
      {
        "name": "Obed Vargas",
        "pos": "MF",
        "shirt": "18",
        "starter": false,
        "ovr": 80,
        "pac": 72,
        "sho": 68,
        "pas": 80,
        "dri": 76,
        "def": 76,
        "phy": 78,
        "sta": 86,
        "restDays": 0,
        "load3": 240,
        "lastRating": 7.0,
        "err3": 0,
        "status": "avail",
        "reason": ""
      },
      {
        "name": "Brian Gutiérrez",
        "pos": "MF",
        "shirt": "26",
        "starter": false,
        "ovr": 80,
        "pac": 72,
        "sho": 68,
        "pas": 80,
        "dri": 76,
        "def": 76,
        "phy": 78,
        "sta": 86,
        "restDays": 0,
        "load3": 240,
        "lastRating": 7.0,
        "err3": 0,
        "status": "avail",
        "reason": ""
      },
      {
        "name": "Álvaro Fidalgo",
        "pos": "MF",
        "shirt": "8",
        "starter": false,
        "ovr": 80,
        "pac": 72,
        "sho": 68,
        "pas": 80,
        "dri": 76,
        "def": 76,
        "phy": 78,
        "sta": 86,
        "restDays": 0,
        "load3": 240,
        "lastRating": 7.0,
        "err3": 0,
        "status": "avail",
        "reason": ""
      },
      {
        "name": "Santiago Gimenez",
        "pos": "MF",
        "shirt": "11",
        "starter": false,
        "ovr": 80,
        "pac": 72,
        "sho": 68,
        "pas": 80,
        "dri": 76,
        "def": 76,
        "phy": 78,
        "sta": 86,
        "restDays": 0,
        "load3": 240,
        "lastRating": 7.0,
        "err3": 0,
        "status": "avail",
        "reason": ""
      },
      {
        "name": "Carlos Acevedo",
        "pos": "MF",
        "shirt": "12",
        "starter": false,
        "ovr": 80,
        "pac": 72,
        "sho": 68,
        "pas": 80,
        "dri": 76,
        "def": 76,
        "phy": 78,
        "sta": 86,
        "restDays": 0,
        "load3": 240,
        "lastRating": 7.0,
        "err3": 0,
        "status": "avail",
        "reason": ""
      }
    ],
    "lineup_confirmed": true,
    "formation": "4-3-3"
  },
  "h2h": {
    "w": 0,
    "d": 1,
    "l": 0,
    "last5": [
      {
        "date": "2026-06-25",
        "home": "Czechia",
        "away": "Mexico",
        "score": "0-3",
        "result": "L"
      }
    ]
  },
  "weather": "clear",
  "generated_at": "2026-06-25T10:24:34.469949+00:00",
  "data_notes": {
    "injuries": "PL：FPL 官方 API；其他聯賽：無免費來源",
    "lineup": "免費方案不含陣容資料",
    "attrs": "球員六維為預設值，待 FIFA CSV 匯入後覆蓋"
  },
  "lineup_source": "espn",
  "lineup_fetched_at": "2026-06-25T10:26:47.942220+00:00"
}